AUTHORS
CHANGELOG.txt
DESCRIPTION
LICENSE
MANIFEST.in
README.rst
setup.cfg
setup.py
bower/__init__.py
bower/models.py
bower/management/__init__.py
bower/management/base.py
bower/management/commands/__init__.py
bower/management/commands/bower_init.py
bower/management/commands/bower_install.py
bower/management/init_files/.bowerrc
bower/management/init_files/.gitignore
bower/management/init_files/bower.json
bower/tests/__init__.py
bower/tests/test_management.py
bower/tests/test_settings.py
bower/tests/test_app/__init__.py
bower/tests/test_app/models.py
jack_bower.egg-info/PKG-INFO
jack_bower.egg-info/SOURCES.txt
jack_bower.egg-info/dependency_links.txt
jack_bower.egg-info/requires.txt
jack_bower.egg-info/top_level.txt