Metadata-Version: 1.0
Name: jack-bower
Version: 0.1.7
Summary: Installing frontend Django dependencies via bower.
